slicers.cpython-312-darwin.so
eighta_lib/analysis_tools.py
eighta_lib/__init__.py
eighta_lib/slicing.py
eighta_lib/test.py
eighta_lib/file_management.py
eighta_lib/.dylibs/libsz.2.0.1.dylib
eighta_lib/.dylibs/libhdf5.310.3.0.dylib
eighta_lib/c_extensions/csr_csc_slicers.c
eighta_lib-0.777.dist-info/RECORD
eighta_lib-0.777.dist-info/WHEEL
eighta_lib-0.777.dist-info/top_level.txt
eighta_lib-0.777.dist-info/METADATA
